resdlem/__init__.py
resdlem/equilibrium.py
resdlem-0.0.3.dist-info/LICENSE.txt
resdlem-0.0.3.dist-info/METADATA
resdlem-0.0.3.dist-info/WHEEL
resdlem-0.0.3.dist-info/top_level.txt
resdlem-0.0.3.dist-info/RECORD
