Metadata-Version: 2.1
Name: resdlem
Version: 0.0.3
Summary: A package to calulate equilibrium function for dlem
Author-email: Thomas Ott <Thomas.ott@dri.edu>
Project-URL: Homepage, https://github.com/ThomasOtt314/resdlem
Project-URL: Issues, https://github.com/ThomasOtt314/resdlem/issues
Classifier: Programming Language :: Python :: 3
Classifier: License :: OSI Approved :: MIT License
Classifier: Operating System :: OS Independent
Requires-Python: >=3.8
License-File: LICENSE.txt
